{
  "processedCount": 397,
  "successCount": 397,
  "failedCount": 0,
  "skippedCount": 0,
  "processedPlaceIds": [
    "ChIJqTev8qoS_oYRJ6xeWleh03k",
    "ChIJx4-ZOdtZXIYRIFq5EX2UtsY",
    "ChIJMZOXOE2nZYYRZlHOZvTCUKE",
    "ChIJ3fB6atnLRIYRh-10pmVzQnk",
    "ChIJpURwgnCHToYRvAxo8JHZXGo",
    "ChIJwXnjECOERoYRj3yOqe4HWUY",
    "ChIJPYREH6WnToYR-exI1g7a0OI",
    "ChIJC-uyX2iHToYRC8tQ3yvN3HQ",
    "ChIJMduR6E5_ToYRQj6w0uR_9O0",
    "ChIJOyd4084hTIYRo7W4t4WE-Rg",
    "ChIJ83vMzqGDRoYR7RXPJqGqapE",
    "ChIJAz_00KHJ-4YRcNF0e9T7RTk",
    "ChIJL26s3lvkV4YRtgA-ctt9HKQ",
    "ChIJhRJ_oPjWQIYR5b1NpJULFCY",
    "ChIJ5ywnjNyaQIYR1bfKQkPPnIg",
    "ChIJo9s7xgOyQIYRfhnWUVBWVmQ",
    "ChIJBQEXyvdpNIYRthxyRBoXzx0",
    "ChIJhcMvevxY54YRp6qKT2QXJzE",
    "ChIJfYpQvHxeaIYRi-FDHFjBuq4",
    "ChIJxaoveUu5QIYRgo_rTAtrJZY",
    "ChIJq0ZSi-_MQIYRvilid9q2O3M",
    "ChIJj7ZH_45bXIYRySL_vTptswQ",
    "ChIJezAdT9idQIYRFfuHGmyRHYE",
    "ChIJH9KKYDQATIYRLetipAQ_LXY",
    "ChIJpeIVl4JdXIYRTEZCV3JsfEE",
    "ChIJQxCfV7U4RYYRzmEX_g6OETc",
    "ChIJLRpHmF2CT4YRjADqc7lbKA0",
    "ChIJTRhSe6dPAYcRLuWkWOcxZWU",
    "ChIJ8_rjTi9mXIYRpwc8vrQGDUU",
    "ChIJA7oWSsu9QIYRfYrBk3KewbQ",
    "ChIJ9SffaATLTYYRv3_aa6VT_vU",
    "ChIJby0i2g5KSoYRVrdSQYfJ7eo",
    "ChIJCQTqzwhFP4YRp4j4W_JBoy0",
    "ChIJEV_f4KI-TIYR0PsF0A0lNg4",
    "ChIJcRCaxIGUQIYRMwIWmeiQQkw",
    "ChIJIy8gnEOoXIYReMIYnWjr7v8",
    "ChIJ84rXaOr43YYR6Azdk20UBZ0",
    "ChIJH51ghJCYToYRNpUGVzRnZtI",
    "ChIJH2fwdAdhToYRbPyQKCTZjwc",
    "ChIJAY5MaoXnQIYRxt4sADnvQak",
    "ChIJD3DIMsulQIYRKug1hVu_0wQ",
    "ChIJ-z_Fc8MTTIYREeu74zX_5t4",
    "ChIJn1c-CboS_oYRrz2HlabH6ZE",
    "ChIJg54XYgDNSYYR7_4UhYko61o",
    "ChIJDWWOufGRToYRmkuUq-fcDHk",
    "ChIJPc-hnUCCToYRfqezsuos-Ow",
    "ChIJu53T_GJcP4YRXk0U5gtfgJE",
    "ChIJzS48o2fTRIYRxmB5EWFEaEE",
    "ChIJf9gYgZ6IToYRjrrkV3RT_BE",
    "ChIJJ3x541xY54YRSMj0HkXCzrA",
    "ChIJazo1nztyToYRnQglZFAv6Iw",
    "ChIJn4XJrA-_QIYRAjudYPD8H5o",
    "ChIJR5FPLIPPRIYRO5awNFMmRhg",
    "ChIJkRHUB4GZToYR7UknaO8CkrU",
    "ChIJRSV-DrZ1XIYRAO-FAKDlU9E",
    "ChIJB3o9L2-YQIYRgxWG1zehtVc",
    "ChIJu00pMVKfZYYRwogHZWAyG7k",
    "ChIJB6rOxAE8TIYRtOVpJBjJmV4",
    "ChIJKx-fZoWcQIYR9FQc-UG0j1k",
    "ChIJjYVQIa64QIYRa5XZGSAuREw",
    "ChIJ7bha9NIlQYYRi7uILE-UYB8",
    "ChIJwaAQTqVhToYRfrfx9UEZCdk",
    "ChIJhTfmzlDLSYYRlT8be3JT_gk",
    "ChIJvVvePRHdQIYRGBKgHt38tM0",
    "ChIJu2YX6yi0RIYRrBTvYTY-yCM",
    "ChIJldKVdA19ToYRomag3jEDWjc",
    "ChIJNeEfGBbVTYYRyN0KvnEnGsU",
    "ChIJOYqXYVA8TIYRPLVN2pxOBV4",
    "ChIJaZWcLqGVPoYRGc6PKck2DdE",
    "ChIJdSxihehT54YRdpDNvEwAMEo",
    "ChIJTfrSPjxyToYRZU-9KZNalLM",
    "ChIJMabQ31uERoYRa5VTZj9-4G0",
    "ChIJfS4Fcz61TYYRWe8aAAV6Wb4",
    "ChIJF0bOI64uTIYRZv5YrEZAPMU",
    "ChIJhSCWoOPjQIYRL9_otm-gzfY",
    "ChIJ1Y71iYVYXIYR79s74JNPkj8",
    "ChIJYQXJ8NawQIYRZwEAQj927Og",
    "ChIJUzF4iAXYTYYRPds8t8huOOI",
    "ChIJp0bRtJY8TIYRZ9j7Ly4svS8",
    "ChIJGRedflS-QIYRAv0bpXGeSI4",
    "ChIJ7RinpH9E54YRf1qK7Pis1rE",
    "ChIJ0TpwXPyfP4YR5n_viaBOn5s",
    "ChIJI--7yVvEQIYRScT9Bit8LbE",
    "ChIJ4fXcdDTNRIYR_9hFN3lkKWY",
    "ChIJa_1AKdswR4YRZdPUn2Qhyhc",
    "ChIJ9QIrtzIXTIYRyNifq2pMmAg",
    "ChIJDxFbBGe3QIYRjCNgxaFeFVw",
    "ChIJIXKkC-iYToYRMQzKJbLOJQA",
    "ChIJvQLAE1kMToYRGFi-kHa1E3k",
    "ChIJDf2047kjYYYRDQ5LOu4F_kY",
    "ChIJ3xSF5aAgYYYRWWo2w9Sb2nE",
    "ChIJ312rkC4St4cR5k5t4tthtP8",
    "ChIJsxdKT30MToYRxdWj96ERoag",
    "ChIJW52b6ptATIYRIZ5Cm1GmDBA",
    "ChIJhUJrI2-CQIYR8dyZqehJQUo",
    "ChIJewFtOKYYTIYRwh7ygR74nDk",
    "ChIJ4e4BNW_mQIYR15AXna1FSJQ",
    "ChIJDbhKUywlTIYRqS3uZKnQoNg",
    "ChIJBeT0p8_1aIYRVmEtE-BTtTo",
    "ChIJD6_PAQJ3ZYYRKSITud3q8s0",
    "ChIJDd4hPc4QTIYRM0bfG7pckMU",
    "ChIJ9S8-IffLPoYRXE7DbinoTtc",
    "ChIJKXERaFiLXIYRtlXAfgA-nM0",
    "ChIJvQphHdR2XIYRXghnr6EaWfk",
    "ChIJwbmeuIRhToYREAA5uK-Oiek",
    "ChIJCVBh9p7bQIYRc0M9hN7pnEw",
    "ChIJ_YI6-PpIRYYR2ksyXd5LFHI",
    "ChIJFzJdIDd3ToYR6DTSeVooNLw",
    "ChIJQzVi9oTZ-4YR7D3WEkI12_E",
    "ChIJ0Wmk7ocmQYYRID1RWEpLHQY",
    "ChIJPdmedR03R4YRn9CVMShojek",
    "ChIJz6f7r-GXXIYR4mxE3WCSBm0",
    "ChIJJwplKFClToYRBrBKn_ixPyw",
    "ChIJCaTP2y7WRIYR_OJa8_4_RVQ",
    "ChIJUUGRUk2BRoYRoFeX_EIeYsU",
    "ChIJLXqdT7cjYYYRNIrsiX0U3jw",
    "ChIJhQgXfsKSXIYR4Nm-pxsMJYE",
    "ChIJVTmrhUKCToYRW3dTgD4yfcM",
    "ChIJHeCVqVElTIYRdVyBTxOp2Pk",
    "ChIJiUjeRJa1RIYRq5kG_aMJOoM",
    "ChIJPRRclQ9D54YRhu-1bRCOd1g",
    "ChIJlcXxvS6CToYRUT7Im53gsVk",
    "ChIJPdHARKGcQIYRIU5mgJtxzLw",
    "ChIJryXLMHOCb4YRXrcOXqXSgk4",
    "ChIJc8VI3S2dQIYRZ6vK7zQaqAw",
    "ChIJae7Km0ymXIYR1WWx-JYILh4",
    "ChIJQy8tGfekToYRl7atXud3OS0",
    "ChIJzXnYTwcsW4YRgNUCFaNpZHs",
    "ChIJ7emb7f72XIYRWisitNHvDWQ",
    "ChIJYbyTgLbyXIYRqJA4opgQOMA",
    "ChIJ2fkl9BKWb4YRf2IgBqu_xhc",
    "ChIJC2PI1c6xQIYRcjV191TlqT8",
    "ChIJoQEcEtsjYYYR6295nTvsz0o",
    "ChIJPeXMxbEnTIYRYB6wxxDJ41U",
    "ChIJEVRP3w4YTIYREGQiVNHu7Y0",
    "ChIJC3Uz6U6RToYRpojK7LoDw6k",
    "ChIJNy7cARjnQIYRLzToiV_YBRc",
    "ChIJZWBs5mcnQYYRL3A1Oc7eIBo",
    "ChIJLxx1KzpIRYYRZcrN3wpZ6r8",
    "ChIJTXB13TOXb4YRSj7zZfHVBwE",
    "ChIJY-X7ypLLRoYROspLJNiPals",
    "ChIJYR9TKA1HToYRklLWUpIafAU",
    "ChIJgejTmQ2NXIYRg4O0nimuA2E",
    "ChIJFy5BzzjKTYYRd5InvDk-YXI",
    "ChIJW1K1aMQzW4YRNTVRROQ95GU",
    "ChIJl1NGTzjBQIYR5vQdfm8PmjY",
    "ChIJ1c7KrUcsTIYRqYwL_p8M-kI",
    "ChIJ5ycxDbWfP4YRO8qcB5wnDRI",
    "ChIJw7de3hadQIYRlRjKNFGPLjY",
    "ChIJc8iFsDQSTIYRcQAvwKpeq2k",
    "ChIJ0epGa_BYXIYRjoZ6TuMvo1Y",
    "ChIJoXuko5LQRIYRVCd1hu26Kc0",
    "ChIJs2kSGopiToYRK_ngMUZYmwI",
    "ChIJdapugW1NOYYRCPC6exQIfy0",
    "ChIJqakirkmiZYYRmIq59Yz9eYw",
    "ChIJm9u58pQZTIYRBDEGiZR0fiM",
    "ChIJidbAzeHI-4YRY_26Y_QylTY",
    "ChIJbS5IgSSkToYRiTaQ6nvy8R0",
    "ChIJnXZ3RkR4ToYRqsiWcIt21oA",
    "ChIJN7q3Y20mTIYRR7GySpUZXRE",
    "ChIJtXgMDJQtTIYRXLIIyk8RzhM",
    "ChIJ9aIMtiXvQIYRP6zC1o4cPqY",
    "ChIJ1SqDvZnlV4YR-QkQHf31fUA",
    "ChIJGSrCKslD54YRcPU5SvuQWL4",
    "ChIJl22YdGvKSYYRajnTV3AiuIs",
    "ChIJuxUM5AVhToYRJZzK37l-Z6s",
    "ChIJJaW0DJj2XIYRaNaLEHzgzX4",
    "ChIJh4nlg1GHXIYRZOKbDPMoMi0",
    "ChIJgz-oAbLEQIYR3T9zF14Y9ZY",
    "ChIJzyswLax3ZYYRkGKIZYqysQU",
    "ChIJtTOqF6CIToYRTCHYSlF-CEs",
    "ChIJbwStRpd3ZYYRzg6E4dhDPCQ",
    "ChIJ_e6jj6nAQIYRP13dCCK6j80",
    "ChIJP9ES5CLXTYYRGgDeedhzCIE",
    "ChIJn8xXH-SDRoYRr8vCY1Rmfog",
    "ChIJ3YQRKVJJRYYRugr5l1m0y38",
    "ChIJdXQn7PpcXIYRGfUg80qZ7Mc",
    "ChIJh9onwGbMSYYRqgiQWblxX3Q",
    "ChIJI5xaMeCwWoYRiKI-WNp2pfU",
    "ChIJXyCepsjNTYYRemAHbtBlHwg",
    "ChIJzwxqMpbnQIYRGjZTr5zFfsQ",
    "ChIJpeHPIMrSRIYR1K9_9zQbu5I",
    "ChIJH341ArWKaIYRGhpRpHF-f7M",
    "ChIJn2IWw0-PTIYRGj-ve-krIFg",
    "ChIJu7slnX3RRIYRBf0TJusgEi0",
    "ChIJ5RX_X3s7TIYRm32w8-VCMQY",
    "ChIJWYg8os9G54YRdtXvChkO44E",
    "ChIJS66DIM-jZYYRTWMSGtQArvM",
    "ChIJU18v4ue2UYYRCq5qQ7hVlEY",
    "ChIJGYUQRBkQNoYRhgI7wVlr7U4",
    "ChIJYZiiBVu-QIYR1nHZkR9wNro",
    "ChIJ45BbyJcoTIYR2roSiOTrBDg",
    "ChIJuab5RDSoToYR4E_JZNE2Ouc",
    "ChIJi0htX9swR4YRv5baNB6r6z8",
    "ChIJF9vTAgCoRoYRsckc2X_xSls",
    "ChIJ5TPsEqPyXIYRgMR6XyIIGZI",
    "ChIJV0Oobk-TQIYRPksWcy0CusM",
    "ChIJd9cvbtqYToYRSYeZJ4q0pa4",
    "ChIJQYl4kVodTIYRT9RH3oxP310",
    "ChIJ7bypeLuCQIYRR0g6eRXHzJU",
    "ChIJfYpQvHxeaIYR2zFi4qjXYp4",
    "ChIJDap3SmtrRYYR2D_PBgJmQx4",
    "ChIJIVPdCchaAYcR21qoF9ykRA4",
    "ChIJxbl2eXuXQIYRCkQRVMeIME4",
    "ChIJ45lgdogrTIYRTv-_4HzLqEw",
    "ChIJT7Cy_Oh8ToYRw4v8dDVuShU",
    "ChIJT7w5teViToYR31HJctja-to",
    "ChIJsWhRHH-qToYRIpOLhWfYaBE",
    "ChIJq5YOrZ-DRoYRBLYqdEKdasI",
    "ChIJvf30DUJE54YRpxVA6P16UN0",
    "ChIJISZYm3CAToYRT8yiikFIwU0",
    "ChIJqREF9YMhTIYRc5Z6eN5djsg",
    "ChIJn9o4lCnCQIYRnkwpIfuZD2k",
    "ChIJ0-LtogyBRoYRmHVly2R2p3U",
    "ChIJo9-lgNiBb4YRPo4muFHuMtc",
    "ChIJKV3lc2kjTIYRhngl3hDJVXU",
    "ChIJ_6UqUW-9TYYRCAJPwq4vxIg",
    "ChIJcdzIsonKRIYR8Kbj7TtGg0c",
    "ChIJe_rosH-gZYYRplVZtglr30s",
    "ChIJKxfmiGFE54YRWrdvxw7HXtY",
    "ChIJvyBYBefzToYRlcfMNBKzNKM",
    "ChIJX9oxLqNJSYYR_ZimNRX_KBE",
    "ChIJP46UG-XRQIYRzNwn0WPWZvA",
    "ChIJ05YcRE-oXIYRjrtJL41mt_U",
    "ChIJ2UNulmaXQIYRWzC2qQWtAhA",
    "ChIJT4lRflsgU4YRq-zr270J2Pk",
    "ChIJrYE6wmvAQIYRXhr_qdpO23k",
    "ChIJ18HXvLJjToYRX3u_SqI374s",
    "ChIJFTvvEnhb54YRmdFlrYlZFOo",
    "ChIJsbDwWRJtToYRjSSka1CFELg",
    "ChIJjZsdle53ToYRVqA0TkIpiIY",
    "ChIJrxv-5RRqRYYRKL0eQZm820E",
    "ChIJAzLoE5zsQIYRT0O1KjolwS4",
    "ChIJRU36OLR4ToYRCbrWTJRNdPY",
    "ChIJkVGSPMYiTIYRDQeyBUH1928",
    "ChIJEXhtAL7RRIYRKbgIHp07bD0",
    "ChIJxfKtZfCXQIYR9wL_N-IVIN4",
    "ChIJtcu7MjfWTYYRxlL_4t3DULI",
    "ChIJPxy8W2c7TIYRmEouOdT4kAM",
    "ChIJz5wjdIqYQIYRFIgDWJqpefY",
    "ChIJeU3nUC4WTIYRQ0qk6gqcoec",
    "ChIJU-bUiAwkYYYRFozgsFfnUho",
    "ChIJoV7JFAnhQIYRHQnCFNtGzHQ",
    "ChIJ-x7_JoCAToYR3FbNq16IQcU",
    "ChIJVWVKzZVhToYRM0VeDBYZTJo",
    "ChIJ7ULjjLeiQIYRRObnD3zgocA",
    "ChIJydBewJMyTIYRCfX5s-dMHiI",
    "ChIJtQFO20hY54YRzX43rCaqYtE",
    "ChIJ92iJxOzZQIYRuhDjEWRNgyw",
    "ChIJj7pxE-DGQIYR_DfsoRcEojw",
    "ChIJA3Vuv_gHXYYRDfQUOc0Nytw",
    "ChIJWwKN3JY3TIYR1nCM-s5OzmA",
    "ChIJZYiA8uHAQIYR7oVJYUu5A80",
    "ChIJmWrUOxIbTIYR8-7GNWrkOWw",
    "ChIJFQ_h42SHToYR3_y0UWTf_xA",
    "ChIJSc05FY4MToYRImBlg_75qAg",
    "ChIJEUslpCmZToYRzcYoM2KTTDI",
    "ChIJT-HPyKWNToYRnWe6G4T1Vnk",
    "ChIJqUajl9HRRIYRHcupOt6yV0w",
    "ChIJtRy02x_SRIYRGtSZSP6cEzE",
    "ChIJ38m6FbGEQIYRgpno4eVzlXs",
    "ChIJ40NXZe3VTYYRI5q4sDL2v-Q",
    "ChIJF69wsbV_P4YRW5Chmzfz7AU",
    "ChIJRcu9fIilZYYRTkpKSZZs9eg",
    "ChIJT_RjB2mvToYRPnhoCgTMMzM",
    "ChIJW0vwAQS4XIYRXx-T-wXRIPc",
    "ChIJt_D01mE2W4YRz_IXfnI0hic",
    "ChIJ7ZaEKXnKPoYRhGAHLTmAfqU",
    "ChIJgReP1tQtW4YR85rqjy2oAVE",
    "ChIJRXRW6TgPXIYR3KreCGPq3WA",
    "ChIJH8tOcveaQIYRstaKdlRZqO4",
    "ChIJm89jCjAtW4YRvLLTqIyedHE",
    "ChIJ9VBrS9yDT4YRS3SvoklOjvs",
    "ChIJAa8i_-JiToYR3ruz5S3a-OM",
    "ChIJTwOVG34IR4YREqz73QLHcSk",
    "ChIJMUhCcC95ToYRfENVoRqMxJA",
    "ChIJL6NcQqPI-4YR2PWm1RrGgvM",
    "ChIJi3YkbF_cQIYRo6vTn6lP2JM",
    "ChIJNzGGbEOlToYR4TXoOQr64aY",
    "ChIJJ0OL9lAuTIYRNzlBUwyePIk",
    "ChIJyyvFLL9c54YRXCUDiRYZyC8",
    "ChIJSX36RV7tXIYR6T_eRD8sO-0",
    "ChIJ6Qmdi03KRIYRgGsUyGtL1Q4",
    "ChIJjZmiIp6nZYYR8E5mQNmgcJY",
    "ChIJLRO3tv7BQIYR1aa02X5tJMU",
    "ChIJbzbNUf2TToYRUmtM0yvNyBg",
    "ChIJ31KPKeAXTIYRUHFYHQsQ_Eg",
    "ChIJMY4Cc3geTIYRq1HiT6sLqcc",
    "ChIJCQhA3b4uT4YRU9Cq19Z9gUM",
    "ChIJkZY6l354ToYRbLm5AcJ2bj0",
    "ChIJbSbLO9Q6TIYR1klTibmNg5U",
    "ChIJhz77hFudToYRyssU-aBhUJo",
    "ChIJS2SmwnHHQIYRjEcoCnLnxaE",
    "ChIJVz3Ck2f1XIYRveUPJdTvSzE",
    "ChIJ1alG4GuUb4YR6ewYKvV6r3M",
    "ChIJeV6vcJ_PRIYRnwObAYSfKH4",
    "ChIJU0b__qh_b4YR_2rl2BVbVBQ",
    "ChIJ0fI_WEOfToYR9vnhBG_JuAU",
    "ChIJb3WLoSOnZYYRDoItRf401e8",
    "ChIJ-5geIzp-ToYRhKW3SYHJpg8",
    "ChIJkcA3Md9RSYYR2B2mjrDqZ78",
    "ChIJy29MzhRbaIYRBLmSlnnTqiw",
    "ChIJWxD9JysvTIYRXmRchv0rMa4",
    "ChIJxZJFCY3bToYRDOerdYfFY9g",
    "ChIJk_dYLSAZTIYRujJ4ZKcUkj0",
    "ChIJl9QXsimOVoYRRXPRTDJ987Q",
    "ChIJXXXwZX6LToYR0JbZzPDtACw",
    "ChIJg83lkz7XTYYRLtvwWS8h-gM",
    "ChIJK7rsnD2LXIYRIDP2ltHFuVM",
    "ChIJS0ZkdiKKXIYRR91o7WF-NXc",
    "ChIJ3WDUFd5zToYRjuOTk7LHD6k",
    "ChIJEwp_KA4gYYYRqu9-_obFFbU",
    "ChIJ4da1gERR54YRuOFRjMjYiYM",
    "ChIJ1ZGsOn8nQYYRzTygYg3EnIo",
    "ChIJE0Vk5D2yQIYRKzPFPnng53c",
    "ChIJAVUZwkdaXIYRo1TcggbZqCQ",
    "ChIJb5cWrIpzToYRZFKIydnUZEw",
    "ChIJm3Vm_jfrQIYRDi8p0pcN6Yo",
    "ChIJ4xQWfhckYYYR94oBAVqIzZY",
    "ChIJ7aA3qZCoXIYRCpwauJoeToU",
    "ChIJbyWgcUzxXIYR2jP4KeJJvQs",
    "ChIJG3XtaMCJQIYRmBwmC98HBsc",
    "ChIJIxNJuxJBTIYRP54un6hJqcc",
    "ChIJXQJCx6JpToYRG7urBdEb0qM",
    "ChIJh3Mtbr2RQIYRS9hEJkDXwOo",
    "ChIJ7QN73300TIYRpJ_y24J-G-Q",
    "ChIJjUgj8aa_QIYR0JKM1VK6Qpo",
    "ChIJ7aFnyu1YXIYR9SNzaFqOQJo",
    "ChIJcZ3-BTlY54YR0-Ofj_xlE4M",
    "ChIJJTZjVHK1RIYRPp_-W4g-rYk",
    "ChIJ_-PKIW7mV4YRVJmTOi-AKN8",
    "ChIJe4kGOtsqR4YRaAs53GCOtfs",
    "ChIJtRDgSJmnToYRb10I5S512tI",
    "ChIJYRH2TB9b54YRppT_hr1OT-s",
    "ChIJv26V9IcmQYYRfoOiwECU4hU",
    "ChIJX7mqt8rMPoYRGLeLgMAjeis",
    "ChIJ59R52RafToYRRbwQaQXu62w",
    "ChIJWybdpdueQIYRE3nEYMFzd3I",
    "ChIJ9YvzxLOfToYRGXFnkEpyF78",
    "ChIJlcQD1SyoQIYRQIqXBSrxFX0",
    "ChIJFVxJlTKDQIYRePPknaVd_I8",
    "ChIJg3tEV4WBb4YRpuZj11uzScI",
    "ChIJ43Za7vy9QIYRYPDiLxkwIqo",
    "ChIJQwkJK9EVTIYRhMQ6gI6A5GI",
    "ChIJ--XwJxL6NYYRkuXRo_rW8RA",
    "ChIJUZDE0O_SRIYRN_ox76ZkxoU",
    "ChIJWeYCDD3vV4YRON1DuFexB-c",
    "ChIJN6vtxJsjTIYR6ep6jtL4OUw",
    "ChIJjwRxuO6HToYRapyK-vT2fiM",
    "ChIJt-AqrKyRQIYRqcHHt3UQX5s",
    "ChIJ7yo46MBhXIYRW2y55NlllH0",
    "ChIJuTky7gctTIYR9hMquj9MGDM",
    "ChIJL2_Ub7cETIYRGr23V8wAvLQ",
    "ChIJtek9y9eeToYRSTX8pqbpqwA",
    "ChIJQ4fVwY5i-YYRX4t9hDzorMg",
    "ChIJUQsIeob1XIYRuks3IcGgWsU",
    "ChIJHQAwK9e4QIYRZ372NE1P7vM",
    "ChIJ4W1uZOTFRIYR0XHIfIfS-Pc",
    "ChIJxY3Z3HYXTIYRpKieZQdeIdM",
    "ChIJ0a9hh5HNQIYRRGIyY6xaw9s",
    "ChIJP4LTp1rvQIYRbNLJvwq2o6c",
    "ChIJ_04W2cFpToYRXGiCLqgBL20",
    "ChIJpSLo7eNZ54YRZyyiS3TBRm4",
    "ChIJjfmKEz7WRIYR2-s9VOWpxAc",
    "ChIJ99MzQxxcXIYRDpKPzg2dMkU",
    "ChIJsRe1BSSnZYYRxKZ_oQxjNxY",
    "ChIJb4QJ8MoJZYYRGCx3ljnDXcs",
    "ChIJ_e35OyeiZYYRi68xiSrc6XA",
    "ChIJTQM1AavjW4YRXSOdfbiSXnQ",
    "ChIJtdU2CY2SXIYRjExE0fINMzM",
    "ChIJcbKaKY4gU4YRTZMkYyo3h3c",
    "ChIJfR4jf9GgZYYROrTAIwx5ieY",
    "ChIJnT1XR8wbTIYRIsQAhhFxoQs",
    "ChIJxcqO6tTqQIYRnAUZYsEpl_s",
    "ChIJaSjR6B8zW4YRVfoS4nYxcyg",
    "ChIJK7UR_n4ETIYRwGm6yX7NOCA",
    "ChIJqYC4IXsyW4YRwjJTsKty0PE",
    "ChIJAxjQGi-gZYYRKvA8Vmw5NJI",
    "ChIJfdu-8NK4QIYRsNk7vR_t9S4",
    "ChIJjdBAK0qfQIYRQyJP7AnQ-5o",
    "ChIJl-xuPdUxOYYR1Bxzn2_RPkM",
    "ChIJ9ac8lC_mS4YRY3FHv2sRx5E",
    "ChIJwdqN0LSPVoYRoydMZef73co",
    "ChIJB97j-cwtTIYR1G5Vh5CXEkA",
    "ChIJj19whhKNVoYREkLAiTR3h8M",
    "ChIJ_YpftbTDQIYR_uTHT_htago",
    "ChIJ7c7gRYXfQIYRlq3WY2P4d3o",
    "ChIJL5dirHxoXIYRc_-H_ds9zwQ",
    "ChIJD6crL1V-ToYRXuUYGJaKHb0",
    "ChIJAbcIkQWDT4YRn_dBQtwn0ck",
    "ChIJz-T8tLwWTIYR3EuOZ3UEufI",
    "ChIJpWiemKHHUIYR2lNu2lfbZiE",
    "ChIJwaxFenCLXIYRUoyh7rj07ik",
    "ChIJb7tmQ7s7TIYR6Dy4Cxc3700",
    "ChIJ6VgNSS03R4YRXeVgqMlsBZY",
    "ChIJxUMAZCXmS4YRcWdsS7GyEfg",
    "ChIJP6_V_OwTTIYRDy6iufpCvmU"
  ],
  "lastProcessedIndex": 396,
  "apiCallsUsed": 3555,
  "imagesUploaded": 15485,
  "imageUploadsFailed": 294,
  "lastUpdated": "2026-02-26T06:33:40.767Z",
  "errors": []
}